aiogram_dependency/__init__.py
aiogram_dependency/dependency.py
aiogram_dependency/middleware.py
aiogram_dependency/registry.py
aiogram_dependency/resolver.py
aiogram_dependency/setup.py
aiogram_dependency/utils.py
aiogram_dependency-1.1.0.dist-info/METADATA
aiogram_dependency-1.1.0.dist-info/WHEEL
aiogram_dependency-1.1.0.dist-info/licenses/LICENSE
aiogram_dependency-1.1.0.dist-info/RECORD
