Metadata-Version: 2.4
Name: aiogram-dependency
Version: 1.1.0
Summary: A FastAPI-style dependency injection system for aiogram Telegram bots. This library brings clean, type-safe dependency injection to your aiogram handlers, making your code more modular, testable, and maintainable.
Author-email: Vladyslav Chaliuk <chaliukvladyslav@gmail.com>
License-File: LICENSE
Requires-Python: >=3.11
Requires-Dist: aiogram>=3.24.0
